kangajo-0.3.0.dist-info/METADATA
kangajo-0.3.0.dist-info/WHEEL
kangajo/__init__.py
kangajo/kangajo.cpython-310-darwin.so
kangajo-0.3.0.dist-info/RECORD
