Metadata-Version: 2.1
Name: kangajo
Version: 0.3.0
Summary: A library to flatten JSON data using Rust.
Author-email: Andrew Mayes <andrewmayes14@hotmail.com>
License: MIT
